pfsense_backup/__init__.py
pfsense_backup/__main__.py
pfsense_backup/cli.py
pfsense_backup-0.2.4.dist-info/LICENSE
pfsense_backup-0.2.4.dist-info/METADATA
pfsense_backup-0.2.4.dist-info/WHEEL
pfsense_backup-0.2.4.dist-info/entry_points.txt
pfsense_backup-0.2.4.dist-info/top_level.txt
pfsense_backup-0.2.4.dist-info/RECORD
