Metadata-Version: 2.1
Name: pfsense_backup
Version: 0.2.4
Summary: A simple tool to fetch backups from the pfSense firewall
Author-email: Stanislav Meduna <stano@meduna.org>
Project-URL: Homepage, https://github.com/numo68/pfsense-backup
Project-URL: Bug Tracker, https://github.com/numo68/pfsense-backup/issues
Classifier: Programming Language :: Python :: 3
Classifier: License :: OSI Approved :: MIT License
Classifier: Operating System :: OS Independent
Requires-Python: >=3.10
License-File: LICENSE
Requires-Dist: PyYAML
Requires-Dist: schema
Requires-Dist: pfbackup
Requires-Dist: prometheus-client
Requires-Dist: urllib3
